matminer/__init__.py
matminer/data_retrieval/__init__.py
matminer/data_retrieval/retrieve_AFLOW.py
matminer/data_retrieval/retrieve_Citrine.py
matminer/data_retrieval/retrieve_MDF.py
matminer/data_retrieval/retrieve_MP.py
matminer/data_retrieval/retrieve_MPDS.py
matminer/data_retrieval/retrieve_MongoDB.py
matminer/data_retrieval/retrieve_base.py
matminer/data_retrieval/tests/__init__.py
matminer/data_retrieval/tests/base.py
matminer/data_retrieval/tests/test_retrieve_AFLOW.py
matminer/data_retrieval/tests/test_retrieve_Citrine.py
matminer/data_retrieval/tests/test_retrieve_MDF.py
matminer/data_retrieval/tests/test_retrieve_MP.py
matminer/data_retrieval/tests/test_retrieve_MPDS.py
matminer/data_retrieval/tests/test_retrieve_MongoDB.py
matminer/datasets/__init__.py
matminer/datasets/convenience_loaders.py
matminer/datasets/dataset_metadata.json
matminer/datasets/dataset_retrieval.py
matminer/datasets/utils.py
matminer/datasets/tests/__init__.py
matminer/datasets/tests/base.py
matminer/datasets/tests/test_convenience_loaders.py
matminer/datasets/tests/test_dataset_retrieval.py
matminer/datasets/tests/test_datasets.py
matminer/datasets/tests/test_utils.py
matminer/featurizers/__init__.py
matminer/featurizers/bandstructure.py
matminer/featurizers/base.py
matminer/featurizers/conversions.py
matminer/featurizers/dos.py
matminer/featurizers/function.py
matminer/featurizers/composition/__init__.py
matminer/featurizers/composition/alloy.py
matminer/featurizers/composition/composite.py
matminer/featurizers/composition/element.py
matminer/featurizers/composition/ion.py
matminer/featurizers/composition/orbital.py
matminer/featurizers/composition/packing.py
matminer/featurizers/composition/thermo.py
matminer/featurizers/composition/tests/__init__.py
matminer/featurizers/composition/tests/base.py
matminer/featurizers/composition/tests/test_alloy.py
matminer/featurizers/composition/tests/test_composite.py
matminer/featurizers/composition/tests/test_element.py
matminer-0.9.3.dist-info/LICENSE
matminer-0.9.3.dist-info/METADATA
matminer-0.9.3.dist-info/WHEEL
matminer-0.9.3.dist-info/top_level.txt
matminer-0.9.3.dist-info/RECORD
