Metadata-Version: 2.1
Name: matminer
Version: 0.9.3
Summary: matminer is a library that contains tools for data mining in Materials Science
Home-page: https://github.com/hackingmaterials/matminer
Author: Anubhav Jain
Author-email: anubhavster@gmail.com
License: modified BSD
Classifier: Programming Language :: Python :: 3.9
Classifier: Programming Language :: Python :: 3.10
Classifier: Programming Language :: Python :: 3.11
Classifier: Development Status :: 4 - Beta
Classifier: Intended Audience :: Science/Research
Classifier: Intended Audience :: System Administrators
Classifier: Intended Audience :: Information Technology
Classifier: Operating System :: OS Independent
Classifier: Topic :: Other/Nonlisted Topic
Classifier: Topic :: Scientific/Engineering
Requires-Python: >=3.9
License-File: LICENSE
Requires-Dist: numpy>=1.23
Requires-Dist: requests~=2.31
Requires-Dist: pandas<3,>=1.5
Requires-Dist: tqdm~=4.66
Requires-Dist: pymongo~=4.5
Requires-Dist: scikit_learn~=1.3
Requires-Dist: sympy~=1.11
Requires-Dist: monty>=2023
Requires-Dist: pymatgen>=2023
Provides-Extra: mpds
Requires-Dist: ujson; extra == "mpds"
Requires-Dist: jmespath; extra == "mpds"
Requires-Dist: httplib2; extra == "mpds"
Requires-Dist: ase; extra == "mpds"
Requires-Dist: jsonschema; extra == "mpds"
Provides-Extra: dscribe
Requires-Dist: dscribe~=2.1; extra == "dscribe"
Provides-Extra: mdfforge
Requires-Dist: mdf-forge; extra == "mdfforge"
Provides-Extra: aflow
Requires-Dist: aflow; extra == "aflow"
Provides-Extra: citrine
Requires-Dist: citrination-client; extra == "citrine"
Provides-Extra: dev
Requires-Dist: pytest; extra == "dev"
Requires-Dist: pytest-cov; extra == "dev"
Requires-Dist: pytest-timeout; extra == "dev"
Requires-Dist: coverage; extra == "dev"
Requires-Dist: coveralls; extra == "dev"
Requires-Dist: flake8; extra == "dev"
Requires-Dist: black; extra == "dev"
Requires-Dist: pylint; extra == "dev"
Requires-Dist: sphinx; extra == "dev"
Provides-Extra: tests
Requires-Dist: ujson; extra == "tests"
Requires-Dist: jmespath; extra == "tests"
Requires-Dist: httplib2; extra == "tests"
Requires-Dist: ase; extra == "tests"
Requires-Dist: jsonschema; extra == "tests"
Requires-Dist: dscribe~=2.1; extra == "tests"
Requires-Dist: mdf-forge; extra == "tests"
Requires-Dist: aflow; extra == "tests"
Requires-Dist: citrination-client; extra == "tests"
Requires-Dist: pytest; extra == "tests"
Requires-Dist: pytest-cov; extra == "tests"
Requires-Dist: pytest-timeout; extra == "tests"
Requires-Dist: coverage; extra == "tests"
Requires-Dist: coveralls; extra == "tests"
Requires-Dist: flake8; extra == "tests"
Requires-Dist: black; extra == "tests"
Requires-Dist: pylint; extra == "tests"
Requires-Dist: sphinx; extra == "tests"
